Metadata-Version: 2.1
Name: type-heed
Version: 0.1.0
Summary: Auto-remove mypy type: ignore comments from Python source files.
Home-page: https://github.com/janosh/type-heed
Author: Janosh Riebesell
Author-email: janosh.riebesell@gmail.com
License: MIT
Keywords: mypy,type checking,code health,auto-fixer,pre-commit hook
Platform: UNKNOWN
Classifier: Programming Language :: Python :: 3 :: Only
Classifier: Programming Language :: Python :: 3.8
Classifier: Programming Language :: Python :: 3.9
Classifier: Programming Language :: Python :: 3.10
Classifier: License :: OSI Approved :: MIT License
Requires-Python: >=3.8
Provides-Extra: test
